cfoundation/__init__.py
cfoundation/app.py
cfoundation/controller.py
cfoundation/logger.py
cfoundation/service.py
cfoundation-0.3.1.dist-info/METADATA
cfoundation-0.3.1.dist-info/RECORD
cfoundation-0.3.1.dist-info/WHEEL
cfoundation-0.3.1.dist-info/top_level.txt
example/__init__.py
example/__main__.py
example/controllers/__init__.py
example/controllers/base.py
example/services/__init__.py
example/services/greet.py
